buildbot_grid_view/VERSION
buildbot_grid_view/__init__.py
buildbot_grid_view/static/scripts.js
buildbot_grid_view-4.3.0.dist-info/METADATA
buildbot_grid_view-4.3.0.dist-info/WHEEL
buildbot_grid_view-4.3.0.dist-info/entry_points.txt
buildbot_grid_view-4.3.0.dist-info/top_level.txt
buildbot_grid_view-4.3.0.dist-info/RECORD
